app_info.py
mac.py
macloot.py
oui.py
macloot-1.1.0.dist-info/LICENSE
macloot-1.1.0.dist-info/METADATA
macloot-1.1.0.dist-info/WHEEL
macloot-1.1.0.dist-info/entry_points.txt
macloot-1.1.0.dist-info/top_level.txt
macloot-1.1.0.dist-info/RECORD
