Metadata-Version: 2.1
Name: macloot
Version: 1.1.0
Summary: A CLI tool to lookup the Organization (OUI) of MAC addresses, from file or stdin, and/or transform between different MAC address formats.
Home-page: https://github.com/bitcanon/macloot
Author: Mikael Schultz
Author-email: macloot.3jcsb@passmail.net
Classifier: Development Status :: 5 - Production/Stable
Classifier: Intended Audience :: System Administrators
Classifier: License :: OSI Approved :: MIT License
Classifier: Operating System :: OS Independent
Classifier: Programming Language :: Python :: 3
Classifier: Programming Language :: Python :: 3.7
Classifier: Programming Language :: Python :: 3.8
Classifier: Programming Language :: Python :: 3.9
Classifier: Programming Language :: Python :: 3.10
Classifier: Programming Language :: Python :: 3.11
Requires-Python: >=3.7
License-File: LICENSE
Requires-Dist: requests
